urlshortener/__init__.py
urlshortener/__main__.py
urlshortener/redis.py
urlshortener/requesthandler.py
urlshortener/urlshortener.py
urlshortener-1.0.0.dist-info/METADATA
urlshortener-1.0.0.dist-info/WHEEL
urlshortener-1.0.0.dist-info/entry_points.txt
urlshortener-1.0.0.dist-info/top_level.txt
urlshortener-1.0.0.dist-info/RECORD
